{
  "version": 22,
  "encryptionVariant": "None",
  "name": "FloatingPointClear",
  "hasParentName": false,
  "samplerDefinitionMap": {},
  "propertyFieldMap": {
    "ClearColor": {
      "num": 1,
      "type": 2,
      "hasData": false
    }
  },
  "formatVersion": "V2",
  "dataOnly": true,
  "passMap": {
    "Clear": {
      "bitSet": "1111111111111111",
      "fallback": "",
      "hasDefaultBlendMode": false,
      "flagDefaultValues": {},
      "variantList": [
        {
          "isSupported": true,
          "flags": {},
          "shaderCodes": [
            {
              "platformShaderStage": {
                "stageName": "Vertex",
                "platformName": "ESSL_100",
                "stage": "Vertex",
                "platform": "ESSL_100"
              },
              "shaderCode": {
                "shaderInputMap": {
                  "position": {
                    "type": "Vec3",
                    "attribute": "Position",
                    "isPerInstance": false,
                    "hasPrecisionConstraint": false,
                    "hasInterpolationConstraint": false
                  }
                },
                "sourceHash": 3109262428454822786
              }
            },
            {
              "platformShaderStage": {
                "stageName": "Fragment",
                "platformName": "ESSL_100",
                "stage": "Fragment",
                "platform": "ESSL_100"
              },
              "shaderCode": {
                "shaderInputMap": {},
                "sourceHash": -2376288530709671798
              }
            },
            {
              "platformShaderStage": {
                "stageName": "Vertex",
                "platformName": "ESSL_310",
                "stage": "Vertex",
                "platform": "ESSL_310"
              },
              "shaderCode": {
                "shaderInputMap": {
                  "position": {
                    "type": "Vec3",
                    "attribute": "Position",
                    "isPerInstance": false,
                    "hasPrecisionConstraint": false,
                    "hasInterpolationConstraint": false
                  }
                },
                "sourceHash": -7159681222757879258
              }
            },
            {
              "platformShaderStage": {
                "stageName": "Fragment",
                "platformName": "ESSL_310",
                "stage": "Fragment",
                "platform": "ESSL_310"
              },
              "shaderCode": {
                "shaderInputMap": {},
                "sourceHash": -2964673824592984585
              }
            }
          ]
        }
      ]
    }
  }
}