{
  "version": 22,
  "encryptionVariant": "None",
  "name": "Gameface/ClearQuad",
  "hasParentName": false,
  "samplerDefinitionMap": {},
  "propertyFieldMap": {},
  "formatVersion": "V2",
  "dataOnly": true,
  "passMap": {
    "Transparent": {
      "bitSet": "1111111111111111",
      "fallback": "",
      "hasDefaultBlendMode": false,
      "flagDefaultValues": {},
      "variantList": [
        {
          "isSupported": true,
          "flags": {},
          "shaderCodes": [
            {
              "platformShaderStage": {
                "stageName": "Vertex",
                "platformName": "ESSL_300",
                "stage": "Vertex",
                "platform": "ESSL_300"
              },
              "shaderCode": {
                "shaderInputMap": {
                  "color": {
                    "type": "Vec4",
                    "attribute": "Color0",
                    "isPerInstance": false,
                    "hasPrecisionConstraint": false,
                    "hasInterpolationConstraint": false
                  },
                  "position": {
                    "type": "Vec4",
                    "attribute": "Position",
                    "isPerInstance": false,
                    "hasPrecisionConstraint": false,
                    "hasInterpolationConstraint": false
                  }
                },
                "sourceHash": -5143830589877715763
              }
            },
            {
              "platformShaderStage": {
                "stageName": "Fragment",
                "platformName": "ESSL_300",
                "stage": "Fragment",
                "platform": "ESSL_300"
              },
              "shaderCode": {
                "shaderInputMap": {
                  "color": {
                    "type": "Vec4",
                    "attribute": "TexCoord1",
                    "isPerInstance": false,
                    "hasPrecisionConstraint": false,
                    "hasInterpolationConstraint": false
                  }
                },
                "sourceHash": 2493936281002191294
              }
            }
          ]
        }
      ]
    }
  }
}